{
  "item": {
    "id": "979821292838",
    "restype": "watchface",
    "name": "序列_Kipfel",
    "description": "Kipfel可爱喵",
    "preview": [
      "画板 1.png",
      "画板 4.png",
      "画板 5.png"
    ],
    "icon": "序列LOGO.png",
    "cover": "画板 1.png",
    "author": [
      {
        "name": "ChiHuan0807",
        "bindABAccount": true
      },
      {
        "name": "点击购买~",
        "bindABAccount": true
      }
    ]
  },
  "links": [
    {
      "icon": "coins",
      "title": "购买链接",
      "url": "https://afdian.com/item/eae104f8b26911f0a44d52540025c377"
    }
  ],
  "downloads": {
    "xmrw6": {
      "version": "1.0.4",
      "file_name": "序列_Kipfel_RW6.face"
    },
    "xmb9p": {
      "version": "1.0.4",
      "file_name": "序列_Kipfel_9P.face"
    }
  },
  "ext": {}
}